MANIFEST.in
brainy
setup.py
bin/brainy-config
bin/brainy-daemon
bin/brainy-frames
bin/brainy-project
bin/brainy-web
src/brainy/__init__.py
src/brainy/config.py
src/brainy/daemon.py
src/brainy/errors.py
src/brainy/flags.py
src/brainy/integration.py
src/brainy/log.py
src/brainy/packages.py
src/brainy/tool.py
src/brainy/utils.py
src/brainy/version.py
src/brainy/webserver.py
src/brainy/lib/matlab/getrecpath.m
src/brainy/lib/matlab/onstartup.m
src/brainy/lib/matlab/private/strsplit.m
src/brainy/lib/python/pindent.py
src/brainy/pipes/CustomCode.py
src/brainy/pipes/FileTools.py
src/brainy/pipes/__init__.py
src/brainy/pipes/base.py
src/brainy/pipes/manager.py
src/brainy/process/__init__.py
src/brainy/process/base.py
src/brainy/process/code.py
src/brainy/process/decorator.py
src/brainy/project/__init__.py
src/brainy/project/base.py
src/brainy/project/manager.py
src/brainy/project/report.py
src/brainy/scheduler/__init__.py
src/brainy/scheduler/base.py
src/brainy/scheduler/lsf.py
src/brainy/scheduler/shellcmd.py
src/brainy/workflows/__init__.py
src/brainy/workflows/__init__.pyc
src/brainy/workflows/demo/hello_world.br
src/brainy/workflows/empty/README.md
src/brainy_mind.egg-info/PKG-INFO
src/brainy_mind.egg-info/SOURCES.txt
src/brainy_mind.egg-info/dependency_links.txt
src/brainy_mind.egg-info/pbr.json
src/brainy_mind.egg-info/requires.txt
src/brainy_mind.egg-info/top_level.txt
ui/web/Gruntfile.js
ui/web/Makefile
ui/web/README.md
ui/web/bower.json
ui/web/index.html
ui/web/package.json
ui/web/assets/css/bootstrap-theme.css.map
ui/web/assets/css/bootstrap.css.map
ui/web/assets/css/brainy-project.css
ui/web/assets/fonts/glyphicons-halflings-regular.eot
ui/web/assets/fonts/glyphicons-halflings-regular.svg
ui/web/assets/fonts/glyphicons-halflings-regular.ttf
ui/web/assets/fonts/glyphicons-halflings-regular.woff
ui/web/assets/images/brainy_logo.png
ui/web/assets/js/brainy-project-core.min.js
ui/web/assets/js/brainy-project-main.js
ui/web/src/project.css
ui/web/src/project.js