Metadata-Version: 1.1
Name: brainy-mind
Version: 0.1.18
Summary: brainy is a nimble workflow managing tool which is a part of iBRAIN framework for scientific computation primarily applied for BigData analysis in context of HPC and HTS
Home-page: https://github.com/pelkmanslab/brainy
Author: Yauhen Yakimovich
Author-email: yauhen.yakimovich@uzh.ch
License: MIT
Download-URL: https://github.com/pelkmanslab/brainy/tarball/master
Platform: Linux
Platform: OS-X
Classifier: Topic :: System :: Distributed Computing
Classifier: Topic :: Scientific/Engineering :: Image Recognition
Classifier: Topic :: Scientific/Engineering :: Information Analysis
Classifier: Topic :: Internet :: WWW/HTTP :: Dynamic Content
Classifier: Topic :: System :: Emulators
Classifier: Intended Audience :: Developers
Classifier: Intended Audience :: System Administrators
Classifier: Programming Language :: Python
Classifier: Programming Language :: Unix Shell
Classifier: Programming Language :: Ruby
Classifier: Programming Language :: Java
Classifier: Development Status :: 4 - Beta
Classifier: Operating System :: POSIX :: Linux
Classifier: Operating System :: MacOS
